video_translate/__init__.py
video_translate/__main__.py
video_translate/cli.py
video_translate/config.py
video_translate/models.py
video_translate/pipeline.py
video_translate/subtitle.py
video_translate/summarizer.py
video_translate/transcriber.py
video_translate/translator.py
video_translate/utils.py
video_translate/video.py
video_translate-1.1.0.dist-info/METADATA
video_translate-1.1.0.dist-info/WHEEL
video_translate-1.1.0.dist-info/entry_points.txt
video_translate-1.1.0.dist-info/licenses/LICENSE
video_translate-1.1.0.dist-info/RECORD
