Metadata-Version: 2.4
Name: video-translate
Version: 1.1.0
Summary: 视频英文字幕翻译为中文字幕工具
Project-URL: Homepage, https://github.com/innovationmech/video-translate
Project-URL: Repository, https://github.com/innovationmech/video-translate
Project-URL: Issues, https://github.com/innovationmech/video-translate/issues
Author: Video Translate Team
License: MIT
License-File: LICENSE
Keywords: deepseek,subtitle,translation,video,whisper
Classifier: Development Status :: 4 - Beta
Classifier: Intended Audience :: End Users/Desktop
Classifier: License :: OSI Approved :: MIT License
Classifier: Operating System :: OS Independent
Classifier: Programming Language :: Python :: 3
Classifier: Programming Language :: Python :: 3.10
Classifier: Programming Language :: Python :: 3.11
Classifier: Programming Language :: Python :: 3.12
Classifier: Topic :: Multimedia :: Video
Classifier: Topic :: Text Processing :: Linguistic
Requires-Python: >=3.10
Requires-Dist: openai-whisper>=20231117
Requires-Dist: openai>=1.0.0
Requires-Dist: torch>=2.0.0
Provides-Extra: dev
Requires-Dist: black>=23.0.0; extra == 'dev'
Requires-Dist: mypy>=1.0.0; extra == 'dev'
Requires-Dist: pytest-cov>=4.0.0; extra == 'dev'
Requires-Dist: pytest>=7.0.0; extra == 'dev'
Requires-Dist: ruff>=0.1.0; extra == 'dev'
